eet/__init__.py
eet/binding.py
eet/helpers.py
eet/invoices.py
eet/remote.py
eet/soap_template.xml
eet/types.py
src/__init__.py
czech_eet-1.0.5.dist-info/LICENSE
czech_eet-1.0.5.dist-info/METADATA
czech_eet-1.0.5.dist-info/WHEEL
czech_eet-1.0.5.dist-info/top_level.txt
czech_eet-1.0.5.dist-info/RECORD
