Metadata-Version: 2.1
Name: czech-eet
Version: 1.0.5
Summary: API for EET
Home-page: https://github.com/keombre/python-eet
Author: Keombre
Author-email: keombre8@gmail.com
License: UNKNOWN
Platform: UNKNOWN
Classifier: Programming Language :: Python :: 3
Classifier: License :: OSI Approved :: MIT License
Classifier: Operating System :: OS Independent
Requires-Python: >=3.6
Requires-Dist: cryptography
Requires-Dist: lxml
